cvnn/__init__.py
cvnn/activations.py
cvnn/data.py
cvnn/help.py
cvnn/initialisations.py
cvnn/layers.py
cvnn/model.py
CVNN_Jamie-0.3.0.dist-info/METADATA
CVNN_Jamie-0.3.0.dist-info/WHEEL
CVNN_Jamie-0.3.0.dist-info/top_level.txt
CVNN_Jamie-0.3.0.dist-info/RECORD
