Metadata-Version: 2.1
Name: CVNN-Jamie
Version: 0.3.0
Summary: A neural network framework supporting complex and real-valued neural networks
Home-page: https://github.com/Gunter-The-Third/Jamies_CVNN
Author: Jamie Keegan-Treloar
Author-email: jamie.kt@icloud.com
License: UNKNOWN
Keywords: complex neural network,real neural network,deep learning,numpy
Platform: UNKNOWN
Classifier: Programming Language :: Python :: 3
Classifier: License :: OSI Approved :: MIT License
Classifier: Operating System :: OS Independent
Classifier: Intended Audience :: Science/Research
Classifier: Topic :: Scientific/Engineering :: Artificial Intelligence
Requires-Python: >=3.7
Requires-Dist: numpy
